py_amo/__init__.py
py_amo/async_repositories/__init__.py
py_amo/async_repositories/base_async_repository.py
py_amo/async_repositories/companies_async_repository.py
py_amo/async_repositories/contacts_async_repository.py
py_amo/async_repositories/leads_async_repository.py
py_amo/async_repositories/pipelines_async_repository.py
py_amo/async_repositories/sources_async_repository.py
py_amo/async_repositories/statuses_async_repository.py
py_amo/async_repositories/users_async_repository.py
py_amo/managers/__init__.py
py_amo/managers/base_entity_manager.py
py_amo/repositories/__init__.py
py_amo/repositories/base_repository.py
py_amo/repositories/companies_repository.py
py_amo/repositories/contacts_repository.py
py_amo/repositories/leads_repository.py
py_amo/repositories/pipelines_repository.py
py_amo/repositories/sources_repository.py
py_amo/repositories/statuses_repository.py
py_amo/repositories/users_repository.py
py_amo/schemas/__init__.py
py_amo/schemas/account_schema.py
py_amo/schemas/catalog_element_schema.py
py_amo/schemas/company_schema.py
py_amo/schemas/contact_schema.py
py_amo/schemas/created_entity_schema.py
py_amo/schemas/custom_field_schema.py
py_amo/schemas/entity_link_schema.py
py_amo/schemas/lead_schema.py
py_amo/schemas/pipeline_shema.py
py_amo/schemas/pipeline_status_schema.py
py_amo/schemas/source_shema.py
py_amo/schemas/tag_schema.py
py_amo/schemas/user_schema.py
py_amo/services/__init__.py
py_amo/services/account_manage.py
py_amo/services/amo_session.py
py_amo/services/filters.py
py_amo/utils/__init__.py
py_amo/utils/async_utils.py
py_amo_client-0.1.4.dist-info/METADATA
py_amo_client-0.1.4.dist-info/WHEEL
py_amo_client-0.1.4.dist-info/top_level.txt
py_amo_client-0.1.4.dist-info/RECORD
