Metadata-Version: 2.1
Name: py-amo-client
Version: 0.1.4
Summary: Api client for amoCRM
Home-page: https://github.com/cheboxarov/py_amo.git
Author: cheboxarov
Author-email: lalakasuper2@gmail.com
Classifier: Programming Language :: Python :: 3
Classifier: License :: OSI Approved :: MIT License
Classifier: Operating System :: OS Independent
Requires-Python: >=3.9
Requires-Dist: requests
